irucapy/__init__.py
irucapy/dataclassutil.py
irucapy/exceptions.py
irucapy/httpirucaapi.py
irucapy/irucaapi.py
irucapy/irucaclient.py
irucapy/member.py
irucapy/members.py
irucapy/memberupdate.py
irucapy/room.py
irucapy/types.py
irucapy-0.1.5.dist-info/LICENSE
irucapy-0.1.5.dist-info/METADATA
irucapy-0.1.5.dist-info/WHEEL
irucapy-0.1.5.dist-info/top_level.txt
irucapy-0.1.5.dist-info/RECORD
